flax_trainer/__init__.py
flax_trainer/dataloader.py
flax_trainer/trainer.py
flax_trainer/utils.py
flax_trainer-0.0.0.8.dist-info/METADATA
flax_trainer-0.0.0.8.dist-info/WHEEL
flax_trainer-0.0.0.8.dist-info/top_level.txt
flax_trainer-0.0.0.8.dist-info/RECORD
