Metadata-Version: 2.1
Name: flax-trainer
Version: 0.0.0.8
Summary: Flax Trainer
Home-page: https://github.com/hkjeon13/flax-trainer
Author: Eddie
Author-email: hkjeo13@gmail.com
License: MIT
Classifier: Intended Audience :: Developers
Classifier: Intended Audience :: Science/Research
Classifier: License :: OSI Approved :: MIT License
Classifier: Operating System :: OS Independent
Classifier: Programming Language :: Python :: 3
Requires-Python: >=3
Requires-Dist: transformers
Requires-Dist: datasets
Requires-Dist: evaluate
Requires-Dist: optax
Requires-Dist: jax
Requires-Dist: jaxlib
Requires-Dist: flax (<=0.6.4)
